{
  "_fv": 8,
  "_type": "mob",
  "definition": {
    "mobName": "Chair Entity",
    "mobLabel": "",
    "mobModelName": "Biped",
    "mobModelTexture": "chairentity.png",
    "mobModelGlowTexture": "",
    "modelWidth": 1.0,
    "modelHeight": 1.0,
    "modelShadowSize": 0.1,
    "mountedYOffset": 0.0,
    "hasSpawnEgg": false,
    "spawnEggBaseColor": {
      "value": -1,
      "falpha": 0.0
    },
    "spawnEggDotColor": {
      "value": -1,
      "falpha": 0.0
    },
    "creativeTab": {
      "value": "MISC"
    },
    "isBoss": false,
    "bossBarColor": "PINK",
    "bossBarType": "PROGRESS",
    "equipmentMainHand": {
      "value": ""
    },
    "equipmentOffHand": {
      "value": ""
    },
    "equipmentHelmet": {
      "value": ""
    },
    "equipmentBody": {
      "value": ""
    },
    "equipmentLeggings": {
      "value": ""
    },
    "equipmentBoots": {
      "value": ""
    },
    "mobBehaviourType": "Mob",
    "mobCreatureType": "UNDEFINED",
    "attackStrength": 40,
    "movementSpeed": 0.0,
    "armorBaseValue": 0.0,
    "trackingRange": 64,
    "health": 10,
    "xpAmount": 0,
    "waterMob": false,
    "flyingMob": false,
    "disableCollisions": false,
    "ridable": true,
    "canControlForward": false,
    "canControlStrafe": false,
    "immuneToFire": true,
    "immuneToArrows": true,
    "immuneToFallDamage": true,
    "immuneToCactus": true,
    "immuneToDrowning": true,
    "immuneToLightning": true,
    "immuneToPotions": true,
    "immuneToPlayer": true,
    "mobDrop": {
      "value": ""
    },
    "livingSound": {
      "value": ""
    },
    "hurtSound": {
      "value": ""
    },
    "deathSound": {
      "value": ""
    },
    "spawnParticles": false,
    "particleToSpawn": {
      "value": "EXPLOSION_NORMAL"
    },
    "particleSpawningShape": "Spread",
    "particleSpawningRadious": 0.5,
    "particleAmount": 4,
    "particleSpawningCondition": "ALWAYS",
    "hasAI": true,
    "aiBase": "(none)",
    "aixml": "<xml xmlns=\"https://developers.google.com/blockly/xml\"><block type=\"aitasks_container\" deletable=\"false\" x=\"40\" y=\"40\"/></xml>",
    "breedable": false,
    "breedTriggerItems": [],
    "ranged": false,
    "rangedAttackItem": {
      "value": ""
    },
    "rangedItemType": "Default item",
    "spawnThisMob": true,
    "doesDespawnWhenIdle": true,
    "spawningProbability": 20,
    "mobSpawningType": "monster",
    "minNumberOfMobsPerGroup": 3,
    "maxNumberOfMobsPerGroup": 30,
    "restrictionBiomes": [],
    "spawnInDungeons": false
  }
}