{
  "_fv": 10,
  "_type": "tool",
  "definition": {
    "renderType": 0,
    "texture": "sapphire_axe",
    "customModelName": "Normal",
    "name": "Sapphire Axe",
    "specialInfo": [],
    "creativeTab": {
      "value": "CUSTOM:AetheriaTools"
    },
    "toolType": "Axe",
    "harvestLevel": 3,
    "efficiency": 9.0,
    "attackSpeed": 1.0,
    "enchantability": 9,
    "damageVsEntity": 9.0,
    "usageCount": 1900,
    "blocksAffected": [],
    "hasGlow": false,
    "repairItems": [
      {
        "value": "CUSTOM:SapphireGem"
      }
    ],
    "stayInGridWhenCrafting": false,
    "damageOnCrafting": false
  }
}