{
  "variants": {
    "facing=south": {
      "model": "aetheria:block/mossy_oak_log"
    },
    "facing=north": {
      "model": "aetheria:block/mossy_oak_log"
    },
    "facing=east": {
      "model": "aetheria:block/mossy_oak_log",
      "x": 90
    },
    "facing=west": {
      "model": "aetheria:block/mossy_oak_log",
      "x": 90
    },
    "facing=up": {
      "model": "aetheria:block/mossy_oak_log",
      "x": 90,
      "y": 90
    },
    "facing=down": {
      "model": "aetheria:block/mossy_oak_log",
      "x": 90,
      "y": 90
    }
  }
}